[
  {
    "ContainingType": "ShoppingCartAPI.Controllers.CartController",
    "Method": "GetCart",
    "RelativePath": "api/Cart",
    "HttpMethod": "GET",
    "IsController": true,
    "Order": 0,
    "Parameters": [],
    "ReturnTypes": [
      {
        "Type": "Shopping_Cart_System.Models.Cart",
        "MediaTypes": [
          "text/plain",
          "application/json",
          "text/json"
        ],
        "StatusCode": 200
      }
    ]
  },
  {
    "ContainingType": "ShoppingCartAPI.Controllers.CartController",
    "Method": "RemoveFromCartAlternative",
    "RelativePath": "api/Cart/{productId}",
    "HttpMethod": "DELETE",
    "IsController": true,
    "Order": 0,
    "Parameters": [
      {
        "Name": "productId",
        "Type": "System.Int32",
        "IsRequired": true
      }
    ],
    "ReturnTypes": [
      {
        "Type": "Shopping_Cart_System.Models.Cart",
        "MediaTypes": [
          "text/plain",
          "application/json",
          "text/json"
        ],
        "StatusCode": 200
      }
    ]
  },
  {
    "ContainingType": "ShoppingCartAPI.Controllers.CartController",
    "Method": "AddToCart",
    "RelativePath": "api/Cart/add",
    "HttpMethod": "POST",
    "IsController": true,
    "Order": 0,
    "Parameters": [
      {
        "Name": "request",
        "Type": "Shopping_Cart_System.Models.Requests.AddToCartRequest",
        "IsRequired": true
      }
    ],
    "ReturnTypes": [
      {
        "Type": "Shopping_Cart_System.Models.Cart",
        "MediaTypes": [
          "text/plain",
          "application/json",
          "text/json"
        ],
        "StatusCode": 200
      }
    ]
  },
  {
    "ContainingType": "ShoppingCartAPI.Controllers.CartController",
    "Method": "Checkout",
    "RelativePath": "api/Cart/checkout",
    "HttpMethod": "POST",
    "IsController": true,
    "Order": 0,
    "Parameters": [
      {
        "Name": "request",
        "Type": "Shopping_Cart_System.Models.Requests.CheckoutRequest",
        "IsRequired": true
      }
    ],
    "ReturnTypes": [
      {
        "Type": "Shopping_Cart_System.Models.Responses.CheckoutResponse",
        "MediaTypes": [
          "text/plain",
          "application/json",
          "text/json"
        ],
        "StatusCode": 200
      }
    ]
  },
  {
    "ContainingType": "ShoppingCartAPI.Controllers.CartController",
    "Method": "RemoveFromCart",
    "RelativePath": "api/Cart/remove",
    "HttpMethod": "POST",
    "IsController": true,
    "Order": 0,
    "Parameters": [
      {
        "Name": "request",
        "Type": "Shopping_Cart_System.Models.Requests.RemoveFromCartRequest",
        "IsRequired": true
      }
    ],
    "ReturnTypes": [
      {
        "Type": "Shopping_Cart_System.Models.Cart",
        "MediaTypes": [
          "text/plain",
          "application/json",
          "text/json"
        ],
        "StatusCode": 200
      }
    ]
  },
  {
    "ContainingType": "ShoppingCartAPI.Controllers.CartController",
    "Method": "UpdateQuantity",
    "RelativePath": "api/Cart/Update Quantity",
    "HttpMethod": "POST",
    "IsController": true,
    "Order": 0,
    "Parameters": [
      {
        "Name": "request",
        "Type": "Shopping_Cart_System.Models.Requests.UpdateCartItemRequest",
        "IsRequired": true
      }
    ],
    "ReturnTypes": [
      {
        "Type": "Shopping_Cart_System.Models.Cart",
        "MediaTypes": [
          "text/plain",
          "application/json",
          "text/json"
        ],
        "StatusCode": 200
      }
    ]
  },
  {
    "ContainingType": "Shopping_Cart_System.Controllers.WeatherForecastController",
    "Method": "Get",
    "RelativePath": "WeatherForecast",
    "HttpMethod": "GET",
    "IsController": true,
    "Order": 0,
    "Parameters": [],
    "ReturnTypes": [
      {
        "Type": "System.Collections.Generic.IEnumerable\u00601[[Shopping_Cart_System.WeatherForecast, Shopping Cart System, Version=1.0.0.0, Culture=neutral, PublicKeyToken=null]]",
        "MediaTypes": [
          "text/plain",
          "application/json",
          "text/json"
        ],
        "StatusCode": 200
      }
    ],
    "EndpointName": "GetWeatherForecast"
  }
]